short_io_api_client/__init__.py
short_io_api_client/api/__init__.py
short_io_api_client/api/domains/__init__.py
short_io_api_client/api/domains/get_api_domains.py
short_io_api_client/api/domains/get_domains_domain_id.py
short_io_api_client/api/domains/post_domains.py
short_io_api_client/api/domains/post_domains_settings_domain_id.py
short_io_api_client/api/link_management/__init__.py
short_io_api_client/api/link_management/delete_links_delete_bulk.py
short_io_api_client/api/link_management/delete_links_link_id.py
short_io_api_client/api/link_management/delete_links_permissions_domain_id_link_id_user_id.py
short_io_api_client/api/link_management/get_links_permissions_domain_id_link_id.py
short_io_api_client/api/link_management/get_links_tweetbot.py
short_io_api_client/api/link_management/post_links.py
short_io_api_client/api/link_management/post_links_archive.py
short_io_api_client/api/link_management/post_links_archive_bulk.py
short_io_api_client/api/link_management/post_links_bulk.py
short_io_api_client/api/link_management/post_links_duplicate_link_id.py
short_io_api_client/api/link_management/post_links_examples.py
short_io_api_client/api/link_management/post_links_link_id.py
short_io_api_client/api/link_management/post_links_permissions_domain_id_link_id_user_id.py
short_io_api_client/api/link_management/post_links_public.py
short_io_api_client/api/link_management/post_links_qr_bulk.py
short_io_api_client/api/link_management/post_links_qr_link_id_string.py
short_io_api_client/api/link_management/post_links_unarchive.py
short_io_api_client/api/link_management/post_links_unarchive_bulk.py
short_io_api_client/api/link_management/post_tags_bulk.py
short_io_api_client/api/link_management/put_links_opengraph_domain_id_link_id.py
short_io_api_client/api/link_queries/__init__.py
short_io_api_client/api/link_queries/get_api_links.py
short_io_api_client/api/link_queries/get_links_by_original_url.py
short_io_api_client/api/link_queries/get_links_expand.py
short_io_api_client-1.0.0.dist-info/METADATA
short_io_api_client-1.0.0.dist-info/WHEEL
short_io_api_client-1.0.0.dist-info/licenses/LICENSE
short_io_api_client-1.0.0.dist-info/RECORD
